NewLib/__init__.py
NewLib/tsquares.py
tsquares/__init__.py
tsquares/tsquares.py
tsquares-0.0.2.dist-info/METADATA
tsquares-0.0.2.dist-info/WHEEL
tsquares-0.0.2.dist-info/top_level.txt
tsquares-0.0.2.dist-info/RECORD
